easyDataverse/__init__.py
easyDataverse/base.py
easyDataverse/classgen.py
easyDataverse/connect.py
easyDataverse/dataset.py
easyDataverse/dataverse.py
easyDataverse/downloader.py
easyDataverse/license.py
easyDataverse/uploader.py
easyDataverse/utils.py
easydataverse-0.4.4.dist-info/LICENSE
easydataverse-0.4.4.dist-info/METADATA
easydataverse-0.4.4.dist-info/WHEEL
easydataverse-0.4.4.dist-info/RECORD
