Metadata-Version: 2.3
Name: easyDataverse
Version: 0.4.4
Summary: Lightweight Dataverse interface in Python to upload, download and update datasets found in Dataverse instances.
License: MIT
Author: Jan Range
Author-email: jan.range@simtech.uni-stuttgart.de
Requires-Python: >=3.9,<4.0
Classifier: License :: OSI Approved :: MIT License
Classifier: Programming Language :: Python :: 3
Classifier: Programming Language :: Python :: 3.9
Classifier: Programming Language :: Python :: 3.10
Classifier: Programming Language :: Python :: 3.11
Classifier: Programming Language :: Python :: 3.12
Classifier: Programming Language :: Python :: 3.13
Requires-Dist: anytree (>=2.12.1,<3.0.0)
Requires-Dist: dotted-dict (==1.1.3)
Requires-Dist: dvuploader (>=0.3.0,<0.4.0)
Requires-Dist: email-validator (>=2.1.1,<3.0.0)
Requires-Dist: httpx (>=0.28,<0.29)
Requires-Dist: nest-asyncio (>=1.6.0,<2.0.0)
Requires-Dist: nob (>=0.8.2,<0.9.0)
Requires-Dist: pyaml (>=24.4.0,<25.0.0)
Requires-Dist: pydantic (>=2.7.1,<3.0.0)
Requires-Dist: pydataverse (>=0.3.1,<0.4.0)
Requires-Dist: python-forge (==18.6.0)
Requires-Dist: rich (>=13.7.1,<14.0.0)
Requires-Dist: xmltodict (>=0.13.0,<0.14.0)
